pybag/__init__.py
pybag/bag_reader.py
pybag/bag_writer.py
pybag/deserialize.py
pybag/mcap_reader.py
pybag/mcap_writer.py
pybag/py.typed
pybag/reader.py
pybag/serialize.py
pybag/translate.py
pybag/types.py
pybag/typestore.py
pybag/bag/__init__.py
pybag/bag/record_parser.py
pybag/bag/record_writer.py
pybag/bag/records.py
pybag/cli/__init__.py
pybag/cli/convert.py
pybag/cli/filter.py
pybag/cli/info.py
pybag/cli/inspect.py
pybag/cli/main.py
pybag/cli/merge.py
pybag/cli/recover.py
pybag/cli/sort.py
pybag/cli/utils.py
pybag/encoding/__init__.py
pybag/encoding/cdr.py
pybag/encoding/rosmsg.py
pybag/io/__init__.py
pybag/io/raw_reader.py
pybag/io/raw_writer.py
pybag/mcap/__init__.py
pybag/mcap/chunk.py
pybag/mcap/crc.py
pybag/mcap/error.py
pybag/mcap/record_encoder.py
pybag/mcap/record_parser.py
pybag/mcap/record_reader.py
pybag/mcap/record_writer.py
pybag/mcap/records.py
pybag/mcap/summary.py
pybag/ros1/__init__.py
pybag/ros1/noetic/__init__.py
pybag/ros1/noetic/diagnostic_msgs.py
pybag/ros1/noetic/geometry_msgs.py
pybag/ros1/noetic/nav_msgs.py
pybag/ros1/noetic/sensor_msgs.py
pybag/ros1/noetic/std_msgs.py
pybag/ros1/noetic/tf2_msgs.py
pybag/ros1/noetic/trajectory_msgs.py
pybag/ros1/noetic/visualization_msgs.py
pybag/ros2/__init__.py
pybag/ros2/foxy/__init__.py
pybag/ros2/foxy/builtin_interfaces.py
pybag/ros2/foxy/diagnostic_msgs.py
pybag/ros2/foxy/geometry_msgs.py
pybag/ros2/foxy/nav_msgs.py
pybag/ros2/foxy/sensor_msgs.py
pybag/ros2/foxy/std_msgs.py
pybag/ros2/foxy/tf2_msgs.py
pybag/ros2/foxy/trajectory_msgs.py
pybag/ros2/foxy/visualization_msgs.py
pybag/ros2/galactic/__init__.py
pybag/ros2/galactic/builtin_interfaces.py
pybag/ros2/galactic/diagnostic_msgs.py
pybag/ros2/galactic/geometry_msgs.py
pybag/ros2/galactic/nav_msgs.py
pybag/ros2/galactic/sensor_msgs.py
pybag/ros2/galactic/std_msgs.py
pybag/ros2/galactic/tf2_msgs.py
pybag/ros2/galactic/trajectory_msgs.py
pybag/ros2/galactic/visualization_msgs.py
pybag/ros2/humble/__init__.py
pybag/ros2/humble/builtin_interfaces.py
pybag_sdk-0.12.0.dist-info/METADATA
pybag_sdk-0.12.0.dist-info/WHEEL
pybag_sdk-0.12.0.dist-info/entry_points.txt
pybag_sdk-0.12.0.dist-info/licenses/LICENSE
pybag_sdk-0.12.0.dist-info/RECORD
