Metadata-Version: 2.4
Name: pybag-sdk
Version: 0.12.0
Summary: A Python library to work with bag files without ROS.
Author-email: Angus Stewart <siliconlad@protonmail.com>
License-File: LICENSE
Requires-Python: >=3.10
Requires-Dist: lz4>=4.4.3
Requires-Dist: zstandard>=0.23.0
